django_dbshell_plus/__init__.py
django_dbshell_plus/management/__init__.py
django_dbshell_plus/management/commands/__init__.py
django_dbshell_plus/management/commands/dbshell_plus.py
django_dbshell_plus-1.0.1.dist-info/DESCRIPTION.rst
django_dbshell_plus-1.0.1.dist-info/METADATA
django_dbshell_plus-1.0.1.dist-info/metadata.json
django_dbshell_plus-1.0.1.dist-info/pbr.json
django_dbshell_plus-1.0.1.dist-info/RECORD
django_dbshell_plus-1.0.1.dist-info/top_level.txt
django_dbshell_plus-1.0.1.dist-info/WHEEL
