Metadata-Version: 1.1
Name: django-dbshell-plus
Version: 1.0.1
Summary: A dbshell_plus management command for Django that selects pgcli or mycli when available.
Home-page: https://github.com/simonpercivall/django-dbshell-plus
Author: Simon Percivall
Author-email: percivall@gmail.com
License: BSD
Keywords: django-dbshell-plus
Platform: UNKNOWN
Classifier: Development Status :: 2 - Pre-Alpha
Classifier: Intended Audience :: Developers
Classifier: License :: OSI Approved :: BSD License
Classifier: Natural Language :: English
Classifier: Programming Language :: Python :: 2
Classifier: Programming Language :: Python :: 2.6
Classifier: Programming Language :: Python :: 2.7
Classifier: Programming Language :: Python :: 3
Classifier: Programming Language :: Python :: 3.3
